sc_google_maps_api/__init__.py
sc_google_maps_api/__version__.py
sc_google_maps_api/client.py
sc_google_maps_api/default_headers.py
sc_google_maps_api-1.0.4.dist-info/LICENSE
sc_google_maps_api-1.0.4.dist-info/METADATA
sc_google_maps_api-1.0.4.dist-info/WHEEL
sc_google_maps_api-1.0.4.dist-info/top_level.txt
sc_google_maps_api-1.0.4.dist-info/RECORD
