Metadata-Version: 2.1
Name: sc-google-maps-api
Version: 1.0.4
Summary: Real-Time Google Maps API
Home-page: https://github.com/Scrapeit-Cloud/google-maps-api-python
Author: Roman Milyushkevich
Author-email: roman@scrape-it.cloud
Maintainer: Roman Milyushkevich
Maintainer-email: roman@scrape-it.cloud
License: MIT
Platform: UNKNOWN
Classifier: License :: OSI Approved :: MIT License
Classifier: Programming Language :: Python
Classifier: Programming Language :: Python :: 3
Classifier: Programming Language :: Python :: 3.6
Classifier: Programming Language :: Python :: 3.7
Classifier: Programming Language :: Python :: 3.8
Classifier: Topic :: Software Development :: Libraries :: Python Modules
Requires-Python: >=3.6
License-File: LICENSE
